[
    {
        "centerrdf": "centerrdf",
        "title": "Halo Season 1",
        "season": "Season 1",
        "qulit": "Download 720p",
        "link": "https://drive.google.com/uc?id=1Tcgz2tXZKYZYyACy6UZAmKAa26OL1liy",
        "eps": "1"
    },
    {
        "link": "https://drive.google.com/uc?id=15li4UDX4F0mmKzGVqiO-qMjCUtncv1Kf",
        "centerrdf": "disnun",
        "eps": "2"
    },
    {
        "link": "https://drive.google.com/uc?id=1kBqQ9DJrsd04NoxknrTXiAVg9c4_sPV6",
        "centerrdf": "disnun",
        "eps": "3"
    },
    {
        "link": "https://drive.google.com/uc?id=1QpimUPCTpIDIVkFiZ4cSCz-385d5QzMV",
        "centerrdf": "disnun",
        "eps": "4"
    },
    {
        "link": "https://drive.google.com/uc?id=1izmf7JEBTSS-QHJl8Zy3IkdQ3AtMaNe4",
        "centerrdf": "disnun",
        "eps": "5"
    },
    {
        "link": "https://drive.google.com/uc?id=1jjNNVrdKmHZ4EModYvRkeBiGdALuFBHy",
        "centerrdf": "disnun",
        "eps": "6"
    },
    {
        "link": "https://drive.google.com/uc?id=1G1UgYsn83eUjk1ZO7YHU_k_uZbG4ElBC",
        "centerrdf": "disnun",
        "eps": "7"
    },
    {
        "link": "https://drive.google.com/uc?id=1MkKa4iZAF6AJoQn-K0-4wrzEFJUC8cvC",
        "centerrdf": "disnun",
        "eps": "8"
    },
    {
        "link": "https://drive.google.com/uc?id=1ObqozdXoyQHrJbYS37UW-u_W3fuZi8HK",
        "centerrdf": "disnun",
        "eps": "9"
    }
]