[
    {
        "title": "Moana (2016)",
        "year": "2016",
        "langu": "Dual Audio [Hindi DD5.1 + English]",
        "size": "350MB | 1.1GB | 2.8GB",
        "imgs": "https://m.media-amazon.com/images/M/MV5BMjI4MzU5NTExNF5BMl5BanBnXkFtZTgwNzY1MTEwMDI@._V1_SX300.jpg",
        "rating": "7.6/10",
        "downloadtitl": "Moana (2016) Download Links",
        "story": "Moana is the daughter of the chief of her tribe. Coming from a long line of navigators she sets off for a fabled island with the demigod Maui. Along the voyage, they battle all which the ocean hides, while learning what the power of persistence and faith can accomplish.",
        "screen1": "https://i.imgur.com/EerMkxI.png",
        "screen2": "https://i.imgur.com/YpaV90X.png",
        "screen3": "https://i.imgur.com/jXQQUDP.png",
        "screen4": "https://i.imgur.com/SN4fDb1.png",
        "link480p":"https://drive.google.com/uc?id=1Zyoxop6MibS6eKjNOmpOPu_IvIYDjk8f&confirm=t",
        "link720p":"https://mega.nz/file/nwJjjYJQ#-5gQkoZ9kYdy_ofAwK5si-3YuHAHaDMkY5hAo_c2kfk",
        "link1080p":"https://drive.google.com/uc?id=1AwYE0kO4FAmKo-bPy7cUXeM6YDV0qFiR&confirm=t",
        "playlnik": "https://drive.google.com/file/d/14KSwn4zYsMNdtyUTXbirvC8suYrSpBoh/view"
    }
    
]